mediahub/__init__.py
mediahub/audio/__init__.py
mediahub/audio/audio_player.py
mediahub/backdoors/__init__.py
mediahub/backdoors/start_backdoor.py
mediahub/playlist/__init__.py
mediahub/playlist/playlist_manager.py
mediahub/settings/__init__.py
mediahub/settings/user_settings.py
mediahub/video/__init__.py
mediahub/video/video_player.py
mediahub-0.1.0.dist-info/METADATA
mediahub-0.1.0.dist-info/WHEEL
mediahub-0.1.0.dist-info/top_level.txt
mediahub-0.1.0.dist-info/RECORD
