Metadata-Version: 2.4
Name: mediahub
Version: 0.1.0
Summary: MediaHub multimedia application
Home-page: https://github.com/yourusername/MediaHub
Author: Savage
Author-email: savage@example.com
Requires-Python: >=3.10
Requires-Dist: pygame
Requires-Dist: opencv-python
Dynamic: author
Dynamic: author-email
Dynamic: description
Dynamic: description-content-type
Dynamic: home-page
Dynamic: requires-dist
Dynamic: requires-python
Dynamic: summary
